{"is_source_file": true, "format": "TypeScript", "description": "This file re-exports all exports from the 'calendar.component' file, serving as an index module for calendar-related components.", "external_files": ["./calendar.component"], "external_methods": [], "published": ["*"], "classes": [], "methods": [], "calls": [], "search-terms": ["calendar", "index.ts", "re-export", "frontend", "feature"], "state": 2, "file_id": 46, "knowledge_revision": 100, "git_revision": "", "ctags": [], "hash": "0c0f739f9a515980c81d900ecac84699", "format-version": 4, "code-base-name": "social_media_dashboard_frontend", "filename": "social_media_dashboard_frontend/src/app/features/calendar/index.ts", "revision_history": [{"100": ""}]}