{"is_source_file": false, "format": "", "description": "", "external_files": [], "external_methods": [], "published": [], "classes": [], "methods": [], "calls": [], "search-terms": [], "state": 2, "file_id": 38, "knowledge_revision": 82, "git_revision": "", "hash": "adf64b4fa3e15f1512ad100fd741fb2d", "format-version": 4, "code-base-name": "social_media_dashboard_frontend", "filename": "social_media_dashboard_frontend/src/app/features/analytics/analytics.component.html", "revision_history": [{"82": ""}]}